CHANGES
LICENSE
MANIFEST.in
README
setup.py
Folio.egg-info/PKG-INFO
Folio.egg-info/SOURCES.txt
Folio.egg-info/dependency_links.txt
Folio.egg-info/requires.txt
Folio.egg-info/top_level.txt
folio/__init__.py
folio/builders.py
folio/helpers.py
folio/server.py
folio/ext/__init__.py
folio/ext/mdwnbuilder.py
folio/ext/themes.py
tests/__init__.py
tests/helpers.py
tests/fixtures/__init__.py
tests/fixtures/ext.py
tests/fixtures/src/helloworld.html