Metadata-Version: 1.1
Name: Folio
Version: 0.4
Summary: A Pythonic static website generator based on Jinja2.
Home-page: http://pyfolio.org
Author: Juan M Martínez
Author-email: jm@guide42.com
License: ISC
Platform: any
Classifier: Programming Language :: Python
Classifier: Environment :: Web Environment
Classifier: Development Status :: 3 - Alpha
Classifier: Intended Audience :: Developers
Classifier: License :: OSI Approved :: ISC License (ISCL)
Classifier: Operating System :: OS Independent
Classifier: Topic :: Internet :: WWW/HTTP
Classifier: Topic :: Internet :: WWW/HTTP :: Site Management
Classifier: Topic :: Text Processing
Classifier: Topic :: Text Processing :: Markup
Classifier: Topic :: Text Processing :: Markup :: HTML
Classifier: Topic :: Utilities
